qtextraplot/__init__.py
qtextraplot/helpers.py
qtextraplot/mixins.py
qtextraplot/py.typed
qtextraplot/typing.py
qtextraplot/_mpl/__init__.py
qtextraplot/_mpl/gids.py
qtextraplot/_mpl/interaction.py
qtextraplot/_mpl/plot_base.py
qtextraplot/_mpl/toolbar.py
qtextraplot/_mpl/views.py
qtextraplot/_napari/LICENSE
qtextraplot/_napari/__init__.py
qtextraplot/_napari/_constants.py
qtextraplot/_napari/_enums.py
qtextraplot/_napari/_qt_viewer.py
qtextraplot/_napari/_register.py
qtextraplot/_napari/_utilities.py
qtextraplot/_napari/_wrapper.py
qtextraplot/_napari/mixins.py
qtextraplot/_napari/mouse_actions.py
qtextraplot/_napari/_vispy/__init__.py
qtextraplot/_napari/_vispy/vispy_canvas.py
qtextraplot/_napari/_vispy/overlays/__init__.py
qtextraplot/_napari/_vispy/overlays/color_bar.py
qtextraplot/_napari/_vispy/overlays/color_bar_mpl.py
qtextraplot/_napari/_vispy/overlays/crosshair.py
qtextraplot/_napari/component_controls/__init__.py
qtextraplot/_napari/component_controls/qt_camera_controls.py
qtextraplot/_napari/component_controls/qt_colorbar_controls.py
qtextraplot/_napari/component_controls/qt_crosshair_controls.py
qtextraplot/_napari/component_controls/qt_grid_controls.py
qtextraplot/_napari/component_controls/qt_scalebar_controls.py
qtextraplot/_napari/component_controls/qt_text_overlay_controls.py
qtextraplot/_napari/components/__init__.py
qtextraplot/_napari/components/layerlist.py
qtextraplot/_napari/components/viewer_model.py
qtextraplot/_napari/components/overlays/__init__.py
qtextraplot/_napari/components/overlays/color_bar.py
qtextraplot/_napari/components/overlays/crosshair.py
qtextraplot/_napari/image/__init__.py
qtextraplot/_napari/image/extract.py
qtextraplot/_napari/image/qt_viewer.py
qtextraplot/_napari/image/utilities.py
qtextraplot/_napari/image/wrapper.py
qtextraplot/_napari/image/_qapp_model/__init__.py
qtextraplot/_napari/image/_qapp_model/_qproviders.py
qtextraplot/_napari/image/_vispy/__init__.py
qtextraplot/_napari/image/_vispy/utils.py
qtextraplot-0.1.1.dist-info/METADATA
qtextraplot-0.1.1.dist-info/WHEEL
qtextraplot-0.1.1.dist-info/licenses/LICENSE
qtextraplot-0.1.1.dist-info/RECORD
